CHANGELOG.txt
LICENCE.txt
MANIFEST.in
README.txt
newfile.py
setup.cfg
setup.py
.eggs/README.txt
.eggs/packaging-20.9-py3.9.egg/EGG-INFO/requires.txt
.eggs/packaging-20.9-py3.9.egg/EGG-INFO/top_level.txt
.eggs/packaging-20.9-py3.9.egg/packaging/__about__.py
.eggs/packaging-20.9-py3.9.egg/packaging/__init__.py
.eggs/packaging-20.9-py3.9.egg/packaging/_compat.py
.eggs/packaging-20.9-py3.9.egg/packaging/_structures.py
.eggs/packaging-20.9-py3.9.egg/packaging/_typing.py
.eggs/packaging-20.9-py3.9.egg/packaging/markers.py
.eggs/packaging-20.9-py3.9.egg/packaging/requirements.py
.eggs/packaging-20.9-py3.9.egg/packaging/specifiers.py
.eggs/packaging-20.9-py3.9.egg/packaging/tags.py
.eggs/packaging-20.9-py3.9.egg/packaging/utils.py
.eggs/packaging-20.9-py3.9.egg/packaging/version.py
.eggs/pyparsing-2.4.7-py3.9.egg/pyparsing.py
.eggs/pyparsing-2.4.7-py3.9.egg/EGG-INFO/top_level.txt
.eggs/webencodings-0.5.1-py3.9.egg/EGG-INFO/top_level.txt
.eggs/webencodings-0.5.1-py3.9.egg/webencodings/__init__.py
.eggs/webencodings-0.5.1-py3.9.egg/webencodings/labels.py
.eggs/webencodings-0.5.1-py3.9.egg/webencodings/mklabels.py
.eggs/webencodings-0.5.1-py3.9.egg/webencodings/tests.py
.eggs/webencodings-0.5.1-py3.9.egg/webencodings/x_user_defined.py
Py_table.egg-info/SOURCES.txt
Py_table.egg-info/dependency_links.txt
Py_table.egg-info/top_level.txt
table.egg-info/SOURCES.txt
table.egg-info/dependency_links.txt
table.egg-info/top_level.txt
table_ex.egg-info/PKG-INFO
table_ex.egg-info/SOURCES.txt
table_ex.egg-info/dependency_links.txt
table_ex.egg-info/top_level.txt
tables/__init__.py
tables.egg-info/SOURCES.txt
tables.egg-info/dependency_links.txt
tables.egg-info/top_level.txt
td_table.egg-info/SOURCES.txt
td_table.egg-info/dependency_links.txt
td_table.egg-info/top_level.txt