Metadata-Version: 1.1
Name: table-ex
Version: 1.0
Summary: Simply Calculates Table
Home-page: UNKNOWN
Author: Ansh Dadwal
Author-email: anshdadwal298@gmail.com
License: MIT
Keywords: Downloader
Platform: UNKNOWN
Classifier: Development Status :: 5 - Production/Stable
Classifier: Intended Audience :: Education
Classifier: Operating System :: Microsoft :: Windows :: Windows 10
Classifier: License :: OSI Approved :: MIT License
Classifier: Programming Language :: Python :: 3
